wolf_smartset/__init__.py
wolf_smartset/constants.py
wolf_smartset/create_session.py
wolf_smartset/helpers.py
wolf_smartset/models.py
wolf_smartset/py.typed
wolf_smartset/token_auth.py
wolf_smartset/wolf_client.py
wolf_smartset-0.1.11.dist-info/METADATA
wolf_smartset-0.1.11.dist-info/WHEEL
wolf_smartset-0.1.11.dist-info/top_level.txt
wolf_smartset-0.1.11.dist-info/RECORD
