Metadata-Version: 2.1
Name: wolf-smartset
Version: 0.1.11
Summary: A package to communicate with Wolf Smart Set Cloud
Home-page: https://github.com/adamkrol93/wolf-smartset
Author: Adam Krol
Author-email: adam.krol93@gmail.com
License: UNKNOWN
Platform: UNKNOWN
Classifier: Programming Language :: Python :: 3
Classifier: Operating System :: OS Independent
Requires-Dist: httpx
